README.md
setup.py
dataTAD/__init__.py
dataTAD.egg-info/PKG-INFO
dataTAD.egg-info/SOURCES.txt
dataTAD.egg-info/dependency_links.txt
dataTAD.egg-info/not-zip-safe
dataTAD.egg-info/requires.txt
dataTAD.egg-info/top_level.txt