Metadata-Version: 1.0
Name: dataTAD
Version: 0.31
Summary: A module with sample data to learn Text as Data for Social Science Research
Home-page: http://andreucasas.com/text_as_data/
Author: Andreu Casas
Author-email: acasas2@uw.edu
License: MIT
Platform: UNKNOWN
